setup.py
xyz01/__init__.py
xyz01.egg-info/PKG-INFO
xyz01.egg-info/SOURCES.txt
xyz01.egg-info/dependency_links.txt
xyz01.egg-info/not-zip-safe
xyz01.egg-info/top_level.txt