Metadata-Version: 1.0
Name: xyz01
Version: 0.2
Summary: The test for pypi
Home-page: https://github.com
Author: Test 
Author-email: test@test.com
License: MIT
Platform: UNKNOWN
